sfcompute/__init__.py
sfcompute-0.0.0.dist-info/METADATA
sfcompute-0.0.0.dist-info/WHEEL
sfcompute-0.0.0.dist-info/top_level.txt
sfcompute-0.0.0.dist-info/RECORD
