Metadata-Version: 2.1
Name: sfcompute
Version: 0.0.0
Summary: Coming soon
Author-email: SFCompute <team@sfcompute.com>
Requires-Python: >=3.7
